[{"name":"bpmn","qualifiedName":"bpmn","href":"bpmn/bpmn-library.html","type":"library","overriddenDepth":0,"packageName":"bpmn_dart"},{"name":"Bpmn","qualifiedName":"bpmn.Bpmn","href":"bpmn/Bpmn-class.html","type":"class","overriddenDepth":0,"packageName":"bpmn_dart","enclosedBy":{"name":"bpmn","type":"library"}},{"name":"getDefinitionName","qualifiedName":"bpmn.Bpmn.getDefinitionName","href":"bpmn/Bpmn/getDefinitionName.html","type":"method","overriddenDepth":1,"packageName":"bpmn_dart","enclosedBy":{"name":"Bpmn","type":"class"}},{"name":"getId","qualifiedName":"bpmn.Bpmn.getId","href":"bpmn/Bpmn/getId.html","type":"method","overriddenDepth":1,"packageName":"bpmn_dart","enclosedBy":{"name":"Bpmn","type":"class"}},{"name":"getRoles","qualifiedName":"bpmn.Bpmn.getRoles","href":"bpmn/Bpmn/getRoles.html","type":"method","overriddenDepth":1,"packageName":"bpmn_dart","enclosedBy":{"name":"Bpmn","type":"class"}},{"name":"getSvg","qualifiedName":"bpmn.Bpmn.getSvg","href":"bpmn/Bpmn/getSvg.html","type":"method","overriddenDepth":1,"packageName":"bpmn_dart","enclosedBy":{"name":"Bpmn","type":"class"}},{"name":"getXml","qualifiedName":"bpmn.Bpmn.getXml","href":"bpmn/Bpmn/getXml.html","type":"method","overriddenDepth":1,"packageName":"bpmn_dart","enclosedBy":{"name":"Bpmn","type":"class"}},{"name":"Bpmn.parse","qualifiedName":"bpmn.Bpmn.parse","href":"bpmn/Bpmn/Bpmn.parse.html","type":"constructor","overriddenDepth":0,"packageName":"bpmn_dart","enclosedBy":{"name":"Bpmn","type":"class"}},{"name":"xml","qualifiedName":"bpmn.Bpmn.xml","href":"bpmn/Bpmn/xml.html","type":"property","overriddenDepth":0,"packageName":"bpmn_dart","enclosedBy":{"name":"Bpmn","type":"class"}},{"name":"bpmn_interface","qualifiedName":"bpmn_interface","href":"bpmn_interface/bpmn_interface-library.html","type":"library","overriddenDepth":0,"packageName":"bpmn_dart"},{"name":"BpmnInterface","qualifiedName":"bpmn_interface.BpmnInterface","href":"bpmn_interface/BpmnInterface-class.html","type":"class","overriddenDepth":0,"packageName":"bpmn_dart","enclosedBy":{"name":"bpmn_interface","type":"library"}},{"name":"BpmnInterface","qualifiedName":"bpmn_interface.BpmnInterface.BpmnInterface","href":"bpmn_interface/BpmnInterface/BpmnInterface.html","type":"constructor","overriddenDepth":0,"packageName":"bpmn_dart","enclosedBy":{"name":"BpmnInterface","type":"class"}},{"name":"getDefinitionName","qualifiedName":"bpmn_interface.BpmnInterface.getDefinitionName","href":"bpmn_interface/BpmnInterface/getDefinitionName.html","type":"method","overriddenDepth":0,"packageName":"bpmn_dart","enclosedBy":{"name":"BpmnInterface","type":"class"}},{"name":"getId","qualifiedName":"bpmn_interface.BpmnInterface.getId","href":"bpmn_interface/BpmnInterface/getId.html","type":"method","overriddenDepth":0,"packageName":"bpmn_dart","enclosedBy":{"name":"BpmnInterface","type":"class"}},{"name":"getRoles","qualifiedName":"bpmn_interface.BpmnInterface.getRoles","href":"bpmn_interface/BpmnInterface/getRoles.html","type":"method","overriddenDepth":0,"packageName":"bpmn_dart","enclosedBy":{"name":"BpmnInterface","type":"class"}},{"name":"getSvg","qualifiedName":"bpmn_interface.BpmnInterface.getSvg","href":"bpmn_interface/BpmnInterface/getSvg.html","type":"method","overriddenDepth":0,"packageName":"bpmn_dart","enclosedBy":{"name":"BpmnInterface","type":"class"}},{"name":"getXml","qualifiedName":"bpmn_interface.BpmnInterface.getXml","href":"bpmn_interface/BpmnInterface/getXml.html","type":"method","overriddenDepth":0,"packageName":"bpmn_dart","enclosedBy":{"name":"BpmnInterface","type":"class"}},{"name":"bpmnjs","qualifiedName":"bpmnjs","href":"bpmnjs/bpmnjs-library.html","type":"library","overriddenDepth":0,"packageName":"bpmn_dart"},{"name":"bpmnjs","qualifiedName":"bpmnjs","href":"bpmnjs/bpmnjs-library.html","type":"library","overriddenDepth":0,"packageName":"bpmn_dart"},{"name":"BpmnCanvas","qualifiedName":"bpmnjs.BpmnCanvas","href":"bpmnjs/BpmnCanvas-class.html","type":"class","overriddenDepth":0,"packageName":"bpmn_dart","enclosedBy":{"name":"bpmnjs","type":"library"}},{"name":"BpmnCanvas","qualifiedName":"bpmnjs.BpmnCanvas","href":"bpmnjs/BpmnCanvas-class.html","type":"class","overriddenDepth":0,"packageName":"bpmn_dart","enclosedBy":{"name":"bpmnjs","type":"library"}},{"name":"BpmnCanvas","qualifiedName":"bpmnjs.BpmnCanvas.BpmnCanvas","href":"bpmnjs/BpmnCanvas/BpmnCanvas.html","type":"constructor","overriddenDepth":0,"packageName":"bpmn_dart","enclosedBy":{"name":"BpmnCanvas","type":"class"}},{"name":"BpmnCanvas","qualifiedName":"bpmnjs.BpmnCanvas.BpmnCanvas","href":"bpmnjs/BpmnCanvas/BpmnCanvas.html","type":"constructor","overriddenDepth":0,"packageName":"bpmn_dart","enclosedBy":{"name":"BpmnCanvas","type":"class"}},{"name":"viewbox","qualifiedName":"bpmnjs.BpmnCanvas.viewbox","href":"bpmnjs/BpmnCanvas/viewbox.html","type":"method","overriddenDepth":0,"packageName":"bpmn_dart","enclosedBy":{"name":"BpmnCanvas","type":"class"}},{"name":"viewbox","qualifiedName":"bpmnjs.BpmnCanvas.viewbox","href":"bpmnjs/BpmnCanvas/viewbox.html","type":"method","overriddenDepth":0,"packageName":"bpmn_dart","enclosedBy":{"name":"BpmnCanvas","type":"class"}},{"name":"zoom","qualifiedName":"bpmnjs.BpmnCanvas.zoom","href":"bpmnjs/BpmnCanvas/zoom.html","type":"method","overriddenDepth":0,"packageName":"bpmn_dart","enclosedBy":{"name":"BpmnCanvas","type":"class"}},{"name":"zoom","qualifiedName":"bpmnjs.BpmnCanvas.zoom","href":"bpmnjs/BpmnCanvas/zoom.html","type":"method","overriddenDepth":0,"packageName":"bpmn_dart","enclosedBy":{"name":"BpmnCanvas","type":"class"}},{"name":"BpmnJS","qualifiedName":"bpmnjs.BpmnJS","href":"bpmnjs/BpmnJS-class.html","type":"class","overriddenDepth":0,"packageName":"bpmn_dart","enclosedBy":{"name":"bpmnjs","type":"library"}},{"name":"BpmnJS","qualifiedName":"bpmnjs.BpmnJS.BpmnJS","href":"bpmnjs/BpmnJS/BpmnJS.html","type":"constructor","overriddenDepth":0,"packageName":"bpmn_dart","enclosedBy":{"name":"BpmnJS","type":"class"}},{"name":"get","qualifiedName":"bpmnjs.BpmnJS.get","href":"bpmnjs/BpmnJS/get.html","type":"method","overriddenDepth":0,"packageName":"bpmn_dart","enclosedBy":{"name":"BpmnJS","type":"class"}},{"name":"importXML","qualifiedName":"bpmnjs.BpmnJS.importXML","href":"bpmnjs/BpmnJS/importXML.html","type":"method","overriddenDepth":0,"packageName":"bpmn_dart","enclosedBy":{"name":"BpmnJS","type":"class"}},{"name":"saveSVG","qualifiedName":"bpmnjs.BpmnJS.saveSVG","href":"bpmnjs/BpmnJS/saveSVG.html","type":"method","overriddenDepth":0,"packageName":"bpmn_dart","enclosedBy":{"name":"BpmnJS","type":"class"}},{"name":"saveXML","qualifiedName":"bpmnjs.BpmnJS.saveXML","href":"bpmnjs/BpmnJS/saveXML.html","type":"method","overriddenDepth":0,"packageName":"bpmn_dart","enclosedBy":{"name":"BpmnJS","type":"class"}},{"name":"BpmnOptions","qualifiedName":"bpmnjs.BpmnOptions","href":"bpmnjs/BpmnOptions-class.html","type":"class","overriddenDepth":0,"packageName":"bpmn_dart","enclosedBy":{"name":"bpmnjs","type":"library"}},{"name":"BpmnOptions","qualifiedName":"bpmnjs.BpmnOptions","href":"bpmnjs/BpmnOptions-class.html","type":"class","overriddenDepth":0,"packageName":"bpmn_dart","enclosedBy":{"name":"bpmnjs","type":"library"}},{"name":"BpmnOptions","qualifiedName":"bpmnjs.BpmnOptions.BpmnOptions","href":"bpmnjs/BpmnOptions/BpmnOptions.html","type":"constructor","overriddenDepth":0,"packageName":"bpmn_dart","enclosedBy":{"name":"BpmnOptions","type":"class"}},{"name":"BpmnOptions","qualifiedName":"bpmnjs.BpmnOptions.BpmnOptions","href":"bpmnjs/BpmnOptions/BpmnOptions.html","type":"constructor","overriddenDepth":0,"packageName":"bpmn_dart","enclosedBy":{"name":"BpmnOptions","type":"class"}},{"name":"container","qualifiedName":"bpmnjs.BpmnOptions.container","href":"bpmnjs/BpmnOptions/container.html","type":"property","overriddenDepth":0,"packageName":"bpmn_dart","enclosedBy":{"name":"BpmnOptions","type":"class"}},{"name":"container","qualifiedName":"bpmnjs.BpmnOptions.container","href":"bpmnjs/BpmnOptions/container.html","type":"property","overriddenDepth":0,"packageName":"bpmn_dart","enclosedBy":{"name":"BpmnOptions","type":"class"}},{"name":"BpmnSavedSvgResponse","qualifiedName":"bpmnjs.BpmnSavedSvgResponse","href":"bpmnjs/BpmnSavedSvgResponse-class.html","type":"class","overriddenDepth":0,"packageName":"bpmn_dart","enclosedBy":{"name":"bpmnjs","type":"library"}},{"name":"BpmnSavedSvgResponse","qualifiedName":"bpmnjs.BpmnSavedSvgResponse","href":"bpmnjs/BpmnSavedSvgResponse-class.html","type":"class","overriddenDepth":0,"packageName":"bpmn_dart","enclosedBy":{"name":"bpmnjs","type":"library"}},{"name":"BpmnSavedSvgResponse","qualifiedName":"bpmnjs.BpmnSavedSvgResponse.BpmnSavedSvgResponse","href":"bpmnjs/BpmnSavedSvgResponse/BpmnSavedSvgResponse.html","type":"constructor","overriddenDepth":0,"packageName":"bpmn_dart","enclosedBy":{"name":"BpmnSavedSvgResponse","type":"class"}},{"name":"BpmnSavedSvgResponse","qualifiedName":"bpmnjs.BpmnSavedSvgResponse.BpmnSavedSvgResponse","href":"bpmnjs/BpmnSavedSvgResponse/BpmnSavedSvgResponse.html","type":"constructor","overriddenDepth":0,"packageName":"bpmn_dart","enclosedBy":{"name":"BpmnSavedSvgResponse","type":"class"}},{"name":"svg","qualifiedName":"bpmnjs.BpmnSavedSvgResponse.svg","href":"bpmnjs/BpmnSavedSvgResponse/svg.html","type":"property","overriddenDepth":0,"packageName":"bpmn_dart","enclosedBy":{"name":"BpmnSavedSvgResponse","type":"class"}},{"name":"svg","qualifiedName":"bpmnjs.BpmnSavedSvgResponse.svg","href":"bpmnjs/BpmnSavedSvgResponse/svg.html","type":"property","overriddenDepth":0,"packageName":"bpmn_dart","enclosedBy":{"name":"BpmnSavedSvgResponse","type":"class"}},{"name":"BpmnSavedXmlResponse","qualifiedName":"bpmnjs.BpmnSavedXmlResponse","href":"bpmnjs/BpmnSavedXmlResponse-class.html","type":"class","overriddenDepth":0,"packageName":"bpmn_dart","enclosedBy":{"name":"bpmnjs","type":"library"}},{"name":"BpmnSavedXmlResponse","qualifiedName":"bpmnjs.BpmnSavedXmlResponse","href":"bpmnjs/BpmnSavedXmlResponse-class.html","type":"class","overriddenDepth":0,"packageName":"bpmn_dart","enclosedBy":{"name":"bpmnjs","type":"library"}},{"name":"BpmnSavedXmlResponse","qualifiedName":"bpmnjs.BpmnSavedXmlResponse.BpmnSavedXmlResponse","href":"bpmnjs/BpmnSavedXmlResponse/BpmnSavedXmlResponse.html","type":"constructor","overriddenDepth":0,"packageName":"bpmn_dart","enclosedBy":{"name":"BpmnSavedXmlResponse","type":"class"}},{"name":"BpmnSavedXmlResponse","qualifiedName":"bpmnjs.BpmnSavedXmlResponse.BpmnSavedXmlResponse","href":"bpmnjs/BpmnSavedXmlResponse/BpmnSavedXmlResponse.html","type":"constructor","overriddenDepth":0,"packageName":"bpmn_dart","enclosedBy":{"name":"BpmnSavedXmlResponse","type":"class"}},{"name":"xml","qualifiedName":"bpmnjs.BpmnSavedXmlResponse.xml","href":"bpmnjs/BpmnSavedXmlResponse/xml.html","type":"property","overriddenDepth":0,"packageName":"bpmn_dart","enclosedBy":{"name":"BpmnSavedXmlResponse","type":"class"}},{"name":"xml","qualifiedName":"bpmnjs.BpmnSavedXmlResponse.xml","href":"bpmnjs/BpmnSavedXmlResponse/xml.html","type":"property","overriddenDepth":0,"packageName":"bpmn_dart","enclosedBy":{"name":"BpmnSavedXmlResponse","type":"class"}},{"name":"CanvasViewbox","qualifiedName":"bpmnjs.CanvasViewbox","href":"bpmnjs/CanvasViewbox-class.html","type":"class","overriddenDepth":0,"packageName":"bpmn_dart","enclosedBy":{"name":"bpmnjs","type":"library"}},{"name":"CanvasViewbox","qualifiedName":"bpmnjs.CanvasViewbox","href":"bpmnjs/CanvasViewbox-class.html","type":"class","overriddenDepth":0,"packageName":"bpmn_dart","enclosedBy":{"name":"bpmnjs","type":"library"}},{"name":"CanvasViewbox","qualifiedName":"bpmnjs.CanvasViewbox.CanvasViewbox","href":"bpmnjs/CanvasViewbox/CanvasViewbox.html","type":"constructor","overriddenDepth":0,"packageName":"bpmn_dart","enclosedBy":{"name":"CanvasViewbox","type":"class"}},{"name":"CanvasViewbox","qualifiedName":"bpmnjs.CanvasViewbox.CanvasViewbox","href":"bpmnjs/CanvasViewbox/CanvasViewbox.html","type":"constructor","overriddenDepth":0,"packageName":"bpmn_dart","enclosedBy":{"name":"CanvasViewbox","type":"class"}},{"name":"height","qualifiedName":"bpmnjs.CanvasViewbox.height","href":"bpmnjs/CanvasViewbox/height.html","type":"property","overriddenDepth":0,"packageName":"bpmn_dart","enclosedBy":{"name":"CanvasViewbox","type":"class"}},{"name":"height","qualifiedName":"bpmnjs.CanvasViewbox.height","href":"bpmnjs/CanvasViewbox/height.html","type":"property","overriddenDepth":0,"packageName":"bpmn_dart","enclosedBy":{"name":"CanvasViewbox","type":"class"}},{"name":"width","qualifiedName":"bpmnjs.CanvasViewbox.width","href":"bpmnjs/CanvasViewbox/width.html","type":"property","overriddenDepth":0,"packageName":"bpmn_dart","enclosedBy":{"name":"CanvasViewbox","type":"class"}},{"name":"width","qualifiedName":"bpmnjs.CanvasViewbox.width","href":"bpmnjs/CanvasViewbox/width.html","type":"property","overriddenDepth":0,"packageName":"bpmn_dart","enclosedBy":{"name":"CanvasViewbox","type":"class"}},{"name":"x","qualifiedName":"bpmnjs.CanvasViewbox.x","href":"bpmnjs/CanvasViewbox/x.html","type":"property","overriddenDepth":0,"packageName":"bpmn_dart","enclosedBy":{"name":"CanvasViewbox","type":"class"}},{"name":"x","qualifiedName":"bpmnjs.CanvasViewbox.x","href":"bpmnjs/CanvasViewbox/x.html","type":"property","overriddenDepth":0,"packageName":"bpmn_dart","enclosedBy":{"name":"CanvasViewbox","type":"class"}},{"name":"y","qualifiedName":"bpmnjs.CanvasViewbox.y","href":"bpmnjs/CanvasViewbox/y.html","type":"property","overriddenDepth":0,"packageName":"bpmn_dart","enclosedBy":{"name":"CanvasViewbox","type":"class"}},{"name":"y","qualifiedName":"bpmnjs.CanvasViewbox.y","href":"bpmnjs/CanvasViewbox/y.html","type":"property","overriddenDepth":0,"packageName":"bpmn_dart","enclosedBy":{"name":"CanvasViewbox","type":"class"}},{"name":"NavigatedViewer","qualifiedName":"bpmnjs.NavigatedViewer","href":"bpmnjs/NavigatedViewer-class.html","type":"class","overriddenDepth":0,"packageName":"bpmn_dart","enclosedBy":{"name":"bpmnjs","type":"library"}},{"name":"NavigatedViewer","qualifiedName":"bpmnjs.NavigatedViewer.NavigatedViewer","href":"bpmnjs/NavigatedViewer/NavigatedViewer.html","type":"constructor","overriddenDepth":0,"packageName":"bpmn_dart","enclosedBy":{"name":"NavigatedViewer","type":"class"}},{"name":"get","qualifiedName":"bpmnjs.NavigatedViewer.get","href":"bpmnjs/NavigatedViewer/get.html","type":"method","overriddenDepth":0,"packageName":"bpmn_dart","enclosedBy":{"name":"NavigatedViewer","type":"class"}},{"name":"importXML","qualifiedName":"bpmnjs.NavigatedViewer.importXML","href":"bpmnjs/NavigatedViewer/importXML.html","type":"method","overriddenDepth":0,"packageName":"bpmn_dart","enclosedBy":{"name":"NavigatedViewer","type":"class"}},{"name":"saveSVG","qualifiedName":"bpmnjs.NavigatedViewer.saveSVG","href":"bpmnjs/NavigatedViewer/saveSVG.html","type":"method","overriddenDepth":0,"packageName":"bpmn_dart","enclosedBy":{"name":"NavigatedViewer","type":"class"}},{"name":"saveXML","qualifiedName":"bpmnjs.NavigatedViewer.saveXML","href":"bpmnjs/NavigatedViewer/saveXML.html","type":"method","overriddenDepth":0,"packageName":"bpmn_dart","enclosedBy":{"name":"NavigatedViewer","type":"class"}},{"name":"SaveSVGOptions","qualifiedName":"bpmnjs.SaveSVGOptions","href":"bpmnjs/SaveSVGOptions-class.html","type":"class","overriddenDepth":0,"packageName":"bpmn_dart","enclosedBy":{"name":"bpmnjs","type":"library"}},{"name":"SaveSVGOptions","qualifiedName":"bpmnjs.SaveSVGOptions.SaveSVGOptions","href":"bpmnjs/SaveSVGOptions/SaveSVGOptions.html","type":"constructor","overriddenDepth":0,"packageName":"bpmn_dart","enclosedBy":{"name":"SaveSVGOptions","type":"class"}},{"name":"format","qualifiedName":"bpmnjs.SaveSVGOptions.format","href":"bpmnjs/SaveSVGOptions/format.html","type":"property","overriddenDepth":0,"packageName":"bpmn_dart","enclosedBy":{"name":"SaveSVGOptions","type":"class"}},{"name":"SaveSvgOptions","qualifiedName":"bpmnjs.SaveSvgOptions","href":"bpmnjs/SaveSvgOptions-class.html","type":"class","overriddenDepth":0,"packageName":"bpmn_dart","enclosedBy":{"name":"bpmnjs","type":"library"}},{"name":"SaveSvgOptions","qualifiedName":"bpmnjs.SaveSvgOptions","href":"bpmnjs/SaveSvgOptions-class.html","type":"class","overriddenDepth":0,"packageName":"bpmn_dart","enclosedBy":{"name":"bpmnjs","type":"library"}},{"name":"SaveSvgOptions","qualifiedName":"bpmnjs.SaveSvgOptions.SaveSvgOptions","href":"bpmnjs/SaveSvgOptions/SaveSvgOptions.html","type":"constructor","overriddenDepth":0,"packageName":"bpmn_dart","enclosedBy":{"name":"SaveSvgOptions","type":"class"}},{"name":"SaveSvgOptions","qualifiedName":"bpmnjs.SaveSvgOptions.SaveSvgOptions","href":"bpmnjs/SaveSvgOptions/SaveSvgOptions.html","type":"constructor","overriddenDepth":0,"packageName":"bpmn_dart","enclosedBy":{"name":"SaveSvgOptions","type":"class"}},{"name":"format","qualifiedName":"bpmnjs.SaveSvgOptions.format","href":"bpmnjs/SaveSvgOptions/format.html","type":"property","overriddenDepth":0,"packageName":"bpmn_dart","enclosedBy":{"name":"SaveSvgOptions","type":"class"}},{"name":"format","qualifiedName":"bpmnjs.SaveSvgOptions.format","href":"bpmnjs/SaveSvgOptions/format.html","type":"property","overriddenDepth":0,"packageName":"bpmn_dart","enclosedBy":{"name":"SaveSvgOptions","type":"class"}},{"name":"SaveXMLOptions","qualifiedName":"bpmnjs.SaveXMLOptions","href":"bpmnjs/SaveXMLOptions-class.html","type":"class","overriddenDepth":0,"packageName":"bpmn_dart","enclosedBy":{"name":"bpmnjs","type":"library"}},{"name":"SaveXMLOptions","qualifiedName":"bpmnjs.SaveXMLOptions","href":"bpmnjs/SaveXMLOptions-class.html","type":"class","overriddenDepth":0,"packageName":"bpmn_dart","enclosedBy":{"name":"bpmnjs","type":"library"}},{"name":"SaveXMLOptions","qualifiedName":"bpmnjs.SaveXMLOptions.SaveXMLOptions","href":"bpmnjs/SaveXMLOptions/SaveXMLOptions.html","type":"constructor","overriddenDepth":0,"packageName":"bpmn_dart","enclosedBy":{"name":"SaveXMLOptions","type":"class"}},{"name":"SaveXMLOptions","qualifiedName":"bpmnjs.SaveXMLOptions.SaveXMLOptions","href":"bpmnjs/SaveXMLOptions/SaveXMLOptions.html","type":"constructor","overriddenDepth":0,"packageName":"bpmn_dart","enclosedBy":{"name":"SaveXMLOptions","type":"class"}},{"name":"format","qualifiedName":"bpmnjs.SaveXMLOptions.format","href":"bpmnjs/SaveXMLOptions/format.html","type":"property","overriddenDepth":0,"packageName":"bpmn_dart","enclosedBy":{"name":"SaveXMLOptions","type":"class"}},{"name":"format","qualifiedName":"bpmnjs.SaveXMLOptions.format","href":"bpmnjs/SaveXMLOptions/format.html","type":"property","overriddenDepth":0,"packageName":"bpmn_dart","enclosedBy":{"name":"SaveXMLOptions","type":"class"}},{"name":"getSvgFromModeler","qualifiedName":"bpmnjs.getSvgFromModeler","href":"bpmnjs/getSvgFromModeler.html","type":"function","overriddenDepth":0,"packageName":"bpmn_dart","enclosedBy":{"name":"bpmnjs","type":"library"}},{"name":"getSvgFromViewer","qualifiedName":"bpmnjs.getSvgFromViewer","href":"bpmnjs/getSvgFromViewer.html","type":"function","overriddenDepth":0,"packageName":"bpmn_dart","enclosedBy":{"name":"bpmnjs","type":"library"}},{"name":"getXmlFromModeler","qualifiedName":"bpmnjs.getXmlFromModeler","href":"bpmnjs/getXmlFromModeler.html","type":"function","overriddenDepth":0,"packageName":"bpmn_dart","enclosedBy":{"name":"bpmnjs","type":"library"}},{"name":"getXmlFromModeler","qualifiedName":"bpmnjs.getXmlFromModeler","href":"bpmnjs/getXmlFromModeler.html","type":"function","overriddenDepth":0,"packageName":"bpmn_dart","enclosedBy":{"name":"bpmnjs","type":"library"}},{"name":"setViewboxCenteredAroundPoint","qualifiedName":"bpmnjs.setViewboxCenteredAroundPoint","href":"bpmnjs/setViewboxCenteredAroundPoint.html","type":"function","overriddenDepth":0,"packageName":"bpmn_dart","enclosedBy":{"name":"bpmnjs","type":"library"}},{"name":"setViewboxCenteredAroundPoint","qualifiedName":"bpmnjs.setViewboxCenteredAroundPoint","href":"bpmnjs/setViewboxCenteredAroundPoint.html","type":"function","overriddenDepth":0,"packageName":"bpmn_dart","enclosedBy":{"name":"bpmnjs","type":"library"}}]
